texor/__init__.py
texor/version.py
texor/cli/__init__.py
texor/cli/main.py
texor/cli/wrapper.py
texor/core/__init__.py
texor/core/autograd.py
texor/core/context.py
texor/core/native_backend.py
texor/core/native_tensor.py
texor/core/ops.py
texor/data/__init__.py
texor/data/dataset.py
texor/data/transforms.py
texor/metrics/__init__.py
texor/nn/__init__.py
texor/nn/activations.py
texor/nn/advanced_layers.py
texor/nn/functional.py
texor/nn/layers.py
texor/nn/loss.py
texor/nn/model.py
texor/nn/models/__init__.py
texor/nn/models/gan.py
texor/nn/models/resnet.py
texor/nn/models/transformer.py
texor/optim/__init__.py
texor/optim/optimizers.py
texor-0.1.1.dist-info/licenses/LICENSE
texor-0.1.1.dist-info/METADATA
texor-0.1.1.dist-info/WHEEL
texor-0.1.1.dist-info/entry_points.txt
texor-0.1.1.dist-info/top_level.txt
texor-0.1.1.dist-info/RECORD
